<?xml version="1.0" encoding="utf-8"?>
<Items>
  <Item name="Imperial Aquila Black" identifier="imperialaquilablack" maxstacksize="4" category="Decorative" pickdistance="200" scale="0.5" description="Description" tags="mediumitem" isshootable="True" Indestructible="True" AllowRotatingInEditor="True" CanFlipX="False" CanFlipY="False">
    <Body width="55" height="150" density="10" />
    <Sprite texture="%ModDir%/textures/AquillaBlackTransparent.png" depth="0.845" sourcerect="0,0,150,55" origin="0.5,0.5" />
  </Item>
  <Item name="Imperial Aquila Gold" identifier="imperialaquilagold" maxstacksize="4" category="Decorative" pickdistance="200" scale="0.5" description="Description" tags="mediumitem" isshootable="True" Indestructible="True" AllowRotatingInEditor="True" CanFlipX="False" CanFlipY="False">
    <Body width="150" height="55" density="10" />
    <Sprite texture="%ModDir%/textures/AquillaGoldenTransparent.png" depth="0.845" sourcerect="0,0,150,55" origin="0.5,0.5" />
  </Item>
  <Item name="Adeptus Mechanicus Logo" identifier="adeptusmechanicuslogo" maxstacksize="4" category="Decorative" pickdistance="200" scale="0.5" description="Description" tags="mediumitem" isshootable="True" Indestructible="True" AllowRotatingInEditor="True" CanFlipX="False" CanFlipY="False">
    <Body width="150" height="150" density="10" />
    <Sprite texture="%ModDir%/textures/AdeptusMechanicusTransparent.png" depth="0.845" sourcerect="0,0,150,150" origin="0.5,0.5" />
  </Item>
  <Item name="Banner" identifier="banner" maxstacksize="4" category="Decorative" pickdistance="200" scale="0.5" description="Description" tags="mediumitem" isshootable="True" Indestructible="True" AllowRotatingInEditor="True" CanFlipX="False" CanFlipY="False">
    <Body width="150" height="150" density="10" />
    <Sprite texture="%ModDir%/textures/Banner.png" depth="0.845" sourcerect="0,0,150,150" origin="0.5,0.5" />
  </Item>
  <Item name="AlarmBuzzer Popa" identifier="alarmbuzzerpopa" category="Electrical" Tags="smallitem,sound" maxstacksize="32" maxstacksizecharacterinventory="8" cargocontaineridentifier="metalcrate" scale="0.5" impactsoundtag="impact_metal_light" isshootable="true" GrabWhenSelected="true">
    <PreferredContainer primary="engcab"/>
    <InventoryIcon texture="Content/Items/InventoryIconAtlas.png" sourcerect="191,127,64,64" origin="0.5,0.5" />
    <Sprite texture="Content/Items/Electricity/signalcomp.png" depth="0.8" sourcerect="222,72,40,62" origin="0.5,0.5" />
    <Body radius="20" density="20" />
    <Holdable selectkey="Select" pickkey="Use" slots="Any,RightHand,LeftHand" msg="ItemMsgDetachWrench" PickingTime="5.0" aimpos="65,-10" handle1="0,0" attachable="true" aimable="true">
      <RequiredItem items="wrench" type="Equipped" />
    </Holdable>
    <LightComponent canbeselected="false" lightcolor="255,0,0,100" alphablend="true" castshadows="false" blinkfrequency="2.6" range="20">
      <Sprite texture="Content/Items/Electricity/signalcomp.png" sourcerect="301,963,42,57" origin="0.5,0.5" alpha="1.0" />
      <sound file="%ModDir%/audio/water.ogg" type="OnActive" range="1000.0" loop="true" volume="0.5" />
      <StatusEffect type="OnContained" target="This" IsActive="false">
        <Conditional targetitemcomponent="Holdable" IsActive="eq false" />
      </StatusEffect>
    </LightComponent>
    <ConnectionPanel selectkey="Action" canbeselected="true" msg="ItemMsgRewireScrewdriver" hudpriority="10">
      <GuiFrame relativesize="0.2,0.32" minsize="400,350" maxsize="480,420" anchor="Center" style="ConnectionPanel" />
      <RequiredItem items="screwdriver" type="Equipped" />
      <input name="toggle" displayname="connection.togglestate" />
      <input name="set_state" displayname="connection.setstate" />
    </ConnectionPanel>
  </Item>
</Items>